asgikit-0.18.1.dist-info/METADATA
asgikit-0.18.1.dist-info/WHEEL
asgikit-0.18.1.dist-info/entry_points.txt
asgikit-0.18.1.dist-info/licenses/LICENSE
asgikit/__init__.py
asgikit/__version__.py
asgikit/_constants.py
asgikit/cookies.py
asgikit/exceptions.py
asgikit/files.py
asgikit/forms.py
asgikit/headers.py
asgikit/multidict.py
asgikit/py.typed
asgikit/requests.py
asgikit/requests_body.py
asgikit/responses.py
asgikit/sync.py
asgikit/websockets.py
asgikit-0.18.1.dist-info/RECORD
