Metadata-Version: 2.1
Name: asgikit
Version: 0.18.1
Summary: Toolkit for building ASGI applications and libraries
Keywords: asgi,toolkit,asyncio,web
Author: Livio Ribeiro
License: MIT
Classifier: Development Status :: 4 - Beta
Classifier: Environment :: Web Environment
Classifier: Framework :: AsyncIO
Classifier: Intended Audience :: Developers
Classifier: License :: OSI Approved :: MIT License
Classifier: Operating System :: OS Independent
Classifier: Programming Language :: Python :: 3
Classifier: Programming Language :: Python :: 3.11
Classifier: Programming Language :: Python :: 3.12
Classifier: Programming Language :: Python :: 3.13
Classifier: Programming Language :: Python :: 3.14
Classifier: Topic :: Internet :: WWW/HTTP
Classifier: Topic :: Internet :: WWW/HTTP :: Dynamic Content
Classifier: Topic :: Software Development :: Libraries :: Application Frameworks
Project-URL: Source, https://codeberg.org/python-zayt/asgikit
Project-URL: Documentation, https://python-zayt.codeberg.page/asgikit
Requires-Python: >=3.11
Requires-Dist: anyio~=4.12.0
Requires-Dist: multipart~=1.3.0
